Memento/__init__.py
Memento/models/FaceDetectionWeights.pth
Memento/models/FaceRecognitionWeights.pth
Memento/models/__init__.py
Memento/models/models.py
Memento/utils/__init__.py
Memento/utils/training.py
Memento/utils/utils.py
memento_face-0.1.7.dist-info/METADATA
memento_face-0.1.7.dist-info/WHEEL
memento_face-0.1.7.dist-info/top_level.txt
memento_face-0.1.7.dist-info/RECORD
