Metadata-Version: 2.4
Name: Memento-Face
Version: 0.1.7
Summary: Easy to use Face Recognition and Detection models.
Home-page: https://github.com/RazielMoesch/MementoML
Author: RazielMoesch
Author-email: therazielmoesch@gmail.com
Classifier: Programming Language :: Python :: 3
Classifier: License :: OSI Approved :: MIT License
Classifier: Operating System :: OS Independent
Requires-Python: >=3.9
Requires-Dist: torch>=2.0.0
Requires-Dist: torchvision>=0.15.0
Requires-Dist: opencv-python
Requires-Dist: Pillow
Requires-Dist: matplotlib
Requires-Dist: numpy
Dynamic: author
Dynamic: author-email
Dynamic: classifier
Dynamic: description
Dynamic: description-content-type
Dynamic: home-page
Dynamic: requires-dist
Dynamic: requires-python
Dynamic: summary
